{
  "properties": {
    "displayName": "Develop audit and accountability policies and procedures",
    "policyType": "BuiltIn",
    "mode": "All",
    "description": "CMA_0154 - Develop audit and accountability policies and procedures",
    "metadata": {
      "version": "1.1.0",
      "category": "Regulatory Compliance",
      "additionalMetadataId": "/providers/Microsoft.PolicyInsights/policyMetadata/CMA_0154"
    },
    "version": "1.1.0",
    "parameters": {
      "effect": {
        "type": "String",
        "metadata": {
          "displayName": "Effect",
          "description": "Enable or disable the execution of the policy"
        },
        "allowedValues": [
          "Manual",
          "Disabled"
        ],
        "defaultValue": "Manual"
      }
    },
    "policyRule": {
      "if": {
        "field": "type",
        "equals": "Microsoft.Resources/subscriptions"
      },
      "then": {
        "effect": "[parameters('effect')]",
        "details": {
          "defaultState": "Unknown"
        }
      }
    },
    "versions": [
      "1.1.0"
    ]
  },
  "id": "/providers/Microsoft.Authorization/policyDefinitions/a28323fe-276d-3787-32d2-cef6395764c4",
  "name": "a28323fe-276d-3787-32d2-cef6395764c4"
}