{
  "id": "/providers/Microsoft.Authorization/policyDefinitions/86ccd1bf-e7ad-4851-93ce-6ec817469c1e",
  "name": "86ccd1bf-e7ad-4851-93ce-6ec817469c1e",
  "properties": {
    "description": "Microsoft implements this Personnel Security control",
    "policyType": "Static",
    "metadata": {
      "category": "Regulatory Compliance",
      "version": "1.0.0",
      "additionalMetadataId": "/providers/Microsoft.PolicyInsights/policyMetadata/ACF1507"
    },
    "policyRule": {
      "then": {
        "effect": "audit"
      },
      "if": {
        "allOf": [
          {
            "field": "type",
            "in": [
              "Microsoft.Resources/subscriptions",
              "Microsoft.Resources/subscriptions/resourceGroups"
            ]
          },
          {
            "value": "false",
            "equals": "true"
          }
        ]
      }
    },
    "displayName": "Microsoft Managed Control 1507 - Personnel Security Policy And Procedures"
  }
}
