{
  "id": "/providers/Microsoft.Authorization/policyDefinitions/8d096fe0-f510-4486-8b4d-d17dc230980b",
  "name": "8d096fe0-f510-4486-8b4d-d17dc230980b",
  "properties": {
    "description": "Microsoft implements this Configuration Management control",
    "policyType": "Static",
    "metadata": {
      "category": "Regulatory Compliance",
      "version": "1.0.0",
      "additionalMetadataId": "/providers/Microsoft.PolicyInsights/policyMetadata/ACF1225"
    },
    "policyRule": {
      "then": {
        "effect": "audit"
      },
      "if": {
        "allOf": [
          {
            "field": "type",
            "in": [
              "Microsoft.Resources/subscriptions",
              "Microsoft.Resources/subscriptions/resourceGroups"
            ]
          },
          {
            "value": "false",
            "equals": "true"
          }
        ]
      }
    },
    "displayName": "Microsoft Managed Control 1225 - Information System Component Inventory | Automated Maintenance"
  }
}
