{
  "properties": {
    "displayName": "Microsoft Managed Control 1168 - Continuous Monitoring | Independent Assessment",
    "policyType": "Static",
    "description": "Microsoft implements this Security Assessment and Authorization control",
    "metadata": {
      "version": "1.0.0",
      "category": "Regulatory Compliance",
      "additionalMetadataId": "/providers/Microsoft.PolicyInsights/policyMetadata/ACF1168"
    },
    "version": "1.0.0",
    "policyRule": {
      "if": {
        "allOf": [
          {
            "field": "type",
            "in": [
              "Microsoft.Resources/subscriptions",
              "Microsoft.Resources/subscriptions/resourceGroups"
            ]
          },
          {
            "value": "false",
            "equals": "true"
          }
        ]
      },
      "then": {
        "effect": "audit"
      }
    },
    "versions": [
      "1.0.0"
    ]
  },
  "id": "/providers/Microsoft.Authorization/policyDefinitions/82409f9e-1f32-4775-bf07-b99d53a91b06",
  "name": "82409f9e-1f32-4775-bf07-b99d53a91b06"
}