{
  "properties": {
    "displayName": "Microsoft Managed Control 1421 - Maintenance Personnel",
    "policyType": "Static",
    "description": "Microsoft implements this Maintenance control",
    "metadata": {
      "version": "1.0.0",
      "category": "Regulatory Compliance",
      "additionalMetadataId": "/providers/Microsoft.PolicyInsights/policyMetadata/ACF1421"
    },
    "version": "1.0.0",
    "policyRule": {
      "if": {
        "allOf": [
          {
            "field": "type",
            "in": [
              "Microsoft.Resources/subscriptions",
              "Microsoft.Resources/subscriptions/resourceGroups"
            ]
          },
          {
            "value": "false",
            "equals": "true"
          }
        ]
      },
      "then": {
        "effect": "audit"
      }
    },
    "versions": [
      "1.0.0"
    ]
  },
  "id": "/providers/Microsoft.Authorization/policyDefinitions/e539caaa-da8c-41b8-9e1e-449851e2f7a6",
  "name": "e539caaa-da8c-41b8-9e1e-449851e2f7a6"
}