{
  "properties": {
    "displayName": "[Preview]: System updates should be installed on your machines (powered by Update Center)",
    "policyType": "BuiltIn",
    "mode": "Indexed",
    "description": "Your machines are missing system, security, and critical updates. Software updates often include critical patches to security holes. Such holes are frequently exploited in malware attacks so it's vital to keep your software updated. To install all outstanding patches and secure your machines, follow the remediation steps.",
    "metadata": {
      "version": "1.0.0-preview",
      "preview": true,
      "category": "Security Center"
    },
    "version": "1.0.0-preview",
    "parameters": {
      "effect": {
        "type": "string",
        "defaultValue": "AuditIfNotExists",
        "allowedValues": [
          "AuditIfNotExists",
          "Disabled"
        ],
        "metadata": {
          "displayName": "Effect",
          "description": "Enable or disable the execution of the policy"
        }
      }
    },
    "policyRule": {
      "if": {
        "field": "type",
        "in": [
          "Microsoft.Compute/virtualMachines",
          "Microsoft.HybridCompute/machines"
        ]
      },
      "then": {
        "effect": "[parameters('effect')]",
        "details": {
          "type": "Microsoft.Security/assessments",
          "name": "e1145ab1-eb4f-43d8-911b-36ddf771d13f",
          "existenceCondition": {
            "field": "Microsoft.Security/assessments/status.code",
            "in": [
              "NotApplicable",
              "Healthy"
            ]
          }
        }
      }
    },
    "versions": [
      "1.0.0-PREVIEW"
    ]
  },
  "id": "/providers/Microsoft.Authorization/policyDefinitions/f85bf3e0-d513-442e-89c3-1784ad63382b",
  "name": "f85bf3e0-d513-442e-89c3-1784ad63382b"
}